gannswing.py
gannswing-0.0.1.dist-info/LICENSE
gannswing-0.0.1.dist-info/WHEEL
gannswing-0.0.1.dist-info/METADATA
gannswing-0.0.1.dist-info/RECORD
