Metadata-Version: 2.1
Name: gannswing
Version: 0.0.1
Summary: A Python package for calculating Gann swings
Author-email: David Mitchell <monch1962@gmail.com>
Classifier: License :: OSI Approved :: MIT License
Project-URL: Home, https://github.com/monch1962/gann-swing
